{
    "experiment": {
        "gen_length": 300,
        "num_of_onlookers": 20,
        "gen_num": 10
    },
    "coop_rate": 20,
    "coop_rate_by_gen": {
        "0": 81,
        "1": 78,
        "2": 30,
        "3": 12,
        "4": 0,
        "5": 0,
        "6": 0,
        "7": 0,
        "8": 0,
        "9": 0
    },
    "social_activeness": 80,
    "social_activeness_by_gen": {
        "0": 94,
        "1": 87,
        "2": 78,
        "3": 81,
        "4": 84,
        "5": 71,
        "6": 84,
        "7": 77,
        "8": 71,
        "9": 71
    },
    "positivity_of_gossip_percentage": 98,
    "positivity_of_gossip_percentage_by_gen": {
        "0": 93,
        "1": 96,
        "2": 96,
        "3": 100,
        "4": 100,
        "5": 100,
        "6": 100,
        "7": 100,
        "8": 100,
        "9": 100
    },
    "corrupted_observations": false,
    "community_fitness": 782,
    "fitness_by_generation": {
        "0": 292,
        "1": 289,
        "2": 137,
        "3": 64,
        "4": 0,
        "5": 0,
        "6": 0,
        "7": 0,
        "8": 0,
        "9": 0
    },
    "populations": [
        [
            {
                "strategy": {
                    "donor_strat": "Veritability Discerner",
                    "non_donor_strat": "Spread Positive Trusted",
                    "trust_model": "Balanced Reactor",
                    "options": [
                        -5
                    ]
                },
                "count": 25
            },
            {
                "strategy": {
                    "donor_strat": "Defector",
                    "non_donor_strat": "Lazy",
                    "trust_model": "Void",
                    "options": []
                },
                "count": 2
            },
            {
                "strategy": {
                    "donor_strat": "Defector",
                    "non_donor_strat": "Promote Self",
                    "trust_model": "Void",
                    "options": []
                },
                "count": 2
            },
            {
                "strategy": {
                    "donor_strat": "Defector",
                    "non_donor_strat": "Spread Negative",
                    "trust_model": "Void",
                    "options": []
                },
                "count": 2
            }
        ],
        [
            {
                "strategy": {
                    "donor_strat": "Defector",
                    "non_donor_strat": "Promote Self",
                    "trust_model": "Void",
                    "options": []
                },
                "count": 3
            },
            {
                "strategy": {
                    "donor_strat": "Veritability Discerner",
                    "non_donor_strat": "Spread Positive Trusted",
                    "trust_model": "Balanced Reactor",
                    "options": [
                        -5
                    ]
                },
                "count": 23
            },
            {
                "strategy": {
                    "donor_strat": "Defector",
                    "non_donor_strat": "Lazy",
                    "trust_model": "Void",
                    "options": []
                },
                "count": 4
            },
            {
                "strategy": {
                    "donor_strat": "Defector",
                    "non_donor_strat": "Spread Negative",
                    "trust_model": "Void",
                    "options": []
                },
                "count": 1
            }
        ],
        [
            {
                "strategy": {
                    "donor_strat": "Defector",
                    "non_donor_strat": "Promote Self",
                    "trust_model": "Void",
                    "options": []
                },
                "count": 13
            },
            {
                "strategy": {
                    "donor_strat": "Veritability Discerner",
                    "non_donor_strat": "Spread Positive Trusted",
                    "trust_model": "Balanced Reactor",
                    "options": [
                        -5
                    ]
                },
                "count": 10
            },
            {
                "strategy": {
                    "donor_strat": "Defector",
                    "non_donor_strat": "Lazy",
                    "trust_model": "Void",
                    "options": []
                },
                "count": 7
            },
            {
                "strategy": {
                    "donor_strat": "Defector",
                    "non_donor_strat": "Spread Negative",
                    "trust_model": "Void",
                    "options": []
                },
                "count": 1
            }
        ],
        [
            {
                "strategy": {
                    "donor_strat": "Defector",
                    "non_donor_strat": "Promote Self",
                    "trust_model": "Void",
                    "options": []
                },
                "count": 21
            },
            {
                "strategy": {
                    "donor_strat": "Defector",
                    "non_donor_strat": "Lazy",
                    "trust_model": "Void",
                    "options": []
                },
                "count": 6
            },
            {
                "strategy": {
                    "donor_strat": "Veritability Discerner",
                    "non_donor_strat": "Spread Positive Trusted",
                    "trust_model": "Balanced Reactor",
                    "options": [
                        -5
                    ]
                },
                "count": 4
            }
        ],
        [
            {
                "strategy": {
                    "donor_strat": "Defector",
                    "non_donor_strat": "Promote Self",
                    "trust_model": "Void",
                    "options": []
                },
                "count": 26
            },
            {
                "strategy": {
                    "donor_strat": "Defector",
                    "non_donor_strat": "Lazy",
                    "trust_model": "Void",
                    "options": []
                },
                "count": 5
            }
        ],
        [
            {
                "strategy": {
                    "donor_strat": "Defector",
                    "non_donor_strat": "Promote Self",
                    "trust_model": "Void",
                    "options": []
                },
                "count": 22
            },
            {
                "strategy": {
                    "donor_strat": "Defector",
                    "non_donor_strat": "Lazy",
                    "trust_model": "Void",
                    "options": []
                },
                "count": 9
            }
        ],
        [
            {
                "strategy": {
                    "donor_strat": "Defector",
                    "non_donor_strat": "Promote Self",
                    "trust_model": "Void",
                    "options": []
                },
                "count": 26
            },
            {
                "strategy": {
                    "donor_strat": "Defector",
                    "non_donor_strat": "Lazy",
                    "trust_model": "Void",
                    "options": []
                },
                "count": 5
            }
        ],
        [
            {
                "strategy": {
                    "donor_strat": "Defector",
                    "non_donor_strat": "Promote Self",
                    "trust_model": "Void",
                    "options": []
                },
                "count": 24
            },
            {
                "strategy": {
                    "donor_strat": "Defector",
                    "non_donor_strat": "Lazy",
                    "trust_model": "Void",
                    "options": []
                },
                "count": 7
            }
        ],
        [
            {
                "strategy": {
                    "donor_strat": "Defector",
                    "non_donor_strat": "Promote Self",
                    "trust_model": "Void",
                    "options": []
                },
                "count": 22
            },
            {
                "strategy": {
                    "donor_strat": "Defector",
                    "non_donor_strat": "Lazy",
                    "trust_model": "Void",
                    "options": []
                },
                "count": 9
            }
        ],
        [
            {
                "strategy": {
                    "donor_strat": "Defector",
                    "non_donor_strat": "Promote Self",
                    "trust_model": "Void",
                    "options": []
                },
                "count": 22
            },
            {
                "strategy": {
                    "donor_strat": "Defector",
                    "non_donor_strat": "Lazy",
                    "trust_model": "Void",
                    "options": []
                },
                "count": 9
            }
        ]
    ]
}